MANIFEST.in
README.rst
requirements.txt
setup.cfg
setup.py
pybugsnag/__init__.py
pybugsnag/globals.py
pybugsnag.egg-info/PKG-INFO
pybugsnag.egg-info/SOURCES.txt
pybugsnag.egg-info/dependency_links.txt
pybugsnag.egg-info/not-zip-safe
pybugsnag.egg-info/requires.txt
pybugsnag.egg-info/top_level.txt
pybugsnag/models/__init__.py
pybugsnag/models/client.py
pybugsnag/models/error.py
pybugsnag/test/__init__.py
pybugsnag/test/conftest.py
pybugsnag/test/helpers.py
pybugsnag/test/test_pybugsnag.py
pybugsnag/utils/__init__.py
pybugsnag/utils/text.py