Metadata-Version: 1.1
Name: pybugsnag
Version: 0.0.5
Summary: A python wrapper for the Bugsnag Data Access API
Home-page: https://github.com/jpetrucciani/pybugsnag.git
Author: Jacobi Petrucciani
Author-email: jacobi@mimirhq.com
License: LICENSE
Download-URL: https://github.com/jpetrucciani/pybugsnag.git
Keywords: bugsnag python data api
Platform: UNKNOWN
Classifier: Programming Language :: Python :: 3
Classifier: Programming Language :: Python :: 3.5
Classifier: Programming Language :: Python :: 3.6
Classifier: Programming Language :: Python :: 3.7
